ocelotz/__init__.py
ocelotz/constants.py
ocelotz/display.py
ocelotz/download.py
ocelotz/file_management.py
ocelotz/image_analysis.py
ocelotz/image_conversion.py
ocelotz/image_processing.py
ocelotz/ocelotz.py
ocelotz/parameter_extraction.py
ocelotz/registration.py
ocelotz/segmentation_interface.py
ocelotz/subject_comparison.py
ocelotz/subject_normalization.py
ocelotz/subject_stratification.py
ocelotz/system.py
ocelotz-0.4.2.dist-info/LICENSE.txt
ocelotz-0.4.2.dist-info/METADATA
ocelotz-0.4.2.dist-info/WHEEL
ocelotz-0.4.2.dist-info/entry_points.txt
ocelotz-0.4.2.dist-info/top_level.txt
ocelotz-0.4.2.dist-info/RECORD
